kt_kernel/__init__.py
kt_kernel/_cpu_detect.py
kt_kernel/_kt_kernel_ext_amx.cpython-312-x86_64-linux-gnu.so
kt_kernel/_kt_kernel_ext_avx2.cpython-312-x86_64-linux-gnu.so
kt_kernel/_kt_kernel_ext_avx512_base.cpython-312-x86_64-linux-gnu.so
kt_kernel/_kt_kernel_ext_avx512_bf16.cpython-312-x86_64-linux-gnu.so
kt_kernel/_kt_kernel_ext_avx512_vbmi.cpython-312-x86_64-linux-gnu.so
kt_kernel/_kt_kernel_ext_avx512_vnni.cpython-312-x86_64-linux-gnu.so
kt_kernel/experts.py
kt_kernel/experts_base.py
kt_kernel/cli/__init__.py
kt_kernel/cli/i18n.py
kt_kernel/cli/main.py
kt_kernel/cli/commands/__init__.py
kt_kernel/cli/commands/bench.py
kt_kernel/cli/commands/chat.py
kt_kernel/cli/commands/config.py
kt_kernel/cli/commands/doctor.py
kt_kernel/cli/commands/model.py
kt_kernel/cli/commands/quant.py
kt_kernel/cli/commands/run.py
kt_kernel/cli/commands/sft.py
kt_kernel/cli/commands/version.py
kt_kernel/cli/completions/__init__.py
kt_kernel/cli/completions/_kt
kt_kernel/cli/completions/kt-completion.bash
kt_kernel/cli/completions/kt.fish
kt_kernel/cli/config/__init__.py
kt_kernel/cli/config/settings.py
kt_kernel/cli/utils/__init__.py
kt_kernel/cli/utils/console.py
kt_kernel/cli/utils/environment.py
kt_kernel/cli/utils/model_registry.py
kt_kernel/cli/utils/sglang_checker.py
kt_kernel/utils/__init__.py
kt_kernel/utils/amx.py
kt_kernel/utils/llamafile.py
kt_kernel/utils/loader.py
kt_kernel/utils/moe_kernel.py
kt_kernel-0.5.0.post1.dist-info/METADATA
kt_kernel-0.5.0.post1.dist-info/WHEEL
kt_kernel-0.5.0.post1.dist-info/entry_points.txt
kt_kernel-0.5.0.post1.dist-info/top_level.txt
kt_kernel-0.5.0.post1.dist-info/RECORD
