Metadata-Version: 2.4
Name: kt-kernel
Version: 0.5.0.post1
Summary: KT-Kernel: High-performance kernel operations for KTransformers (AMX/AVX/KML optimizations)
Author: kvcache-ai
License-Expression: Apache-2.0
Project-URL: Homepage, https://github.com/kvcache-ai
Classifier: Programming Language :: Python :: 3
Classifier: Programming Language :: C++
Classifier: Operating System :: POSIX :: Linux
Classifier: Operating System :: MacOS
Requires-Python: >=3.8
Requires-Dist: torch>=2.0.0
Requires-Dist: safetensors>=0.4.0
Requires-Dist: compressed-tensors>=0.7.0
Requires-Dist: numpy>=1.24.0
Requires-Dist: triton>=2.0.0
Requires-Dist: gguf>=0.17.0
Requires-Dist: typer[all]>=0.9.0
Requires-Dist: rich>=13.0.0
Requires-Dist: pyyaml>=6.0
Requires-Dist: httpx>=0.25.0
Requires-Dist: packaging>=23.0
Requires-Dist: black>=25.9.0
Provides-Extra: test
Requires-Dist: pytest>=7.0.0; extra == "test"
Requires-Dist: psutil>=5.9.0; extra == "test"
Dynamic: requires-python
